lcd_module.py
lcd_module-1.1.1.dist-info/METADATA
lcd_module-1.1.1.dist-info/WHEEL
lcd_module-1.1.1.dist-info/top_level.txt
lcd_module-1.1.1.dist-info/RECORD
